README.txt
setup.py
tightocr/__init__.py
tightocr/constants.py
tightocr/library_ctess.py
tightocr/library_lept.py
tightocr/types.py
tightocr.egg-info/PKG-INFO
tightocr.egg-info/SOURCES.txt
tightocr.egg-info/dependency_links.txt
tightocr.egg-info/top_level.txt
tightocr.egg-info/zip-safe
tightocr/adapters/__init__.py
tightocr/adapters/api_adapter.py
tightocr/adapters/lept_adapter.py
tightocr/calls/__init__.py
tightocr/calls/api_calls.py
tightocr/calls/lept_calls.py