Metadata-Version: 1.0
Name: tightocr
Version: 0.4.4
Summary: Thin and pleasant wrapper for Tesseract OCR.
Home-page: https://github.com/dsoprea/TightOCR
Author: Dustin Oprea
Author-email: myselfasunder@gmail.com
License: GPL 2
Keywords: ocr tesseract ctesseract
Platform: UNKNOWN
